Workbook

Sheet Assumptions
A1: Item | B1: Value | C1: Unit | D1: Notes
A2: VPS KVM4 USD / Month | B2: 24.99 | C2: USD | D2: Hostinger KVM4 US (normal/renewal price)
A3: USD to IDR | B3: 16690 | C3: IDR | D3: Exchange rate
A4: VPS Cost IDR / Year | B4: =B2*B3*12 | C4: IDR | D4: Auto calculated
A5: Sites per VPS (max) | B5: 12 | C5: sites | D5: Safe capacity limit
A6: Avg Storage / Site | B6: 5 | C6: GB | D6: Web apps + MySQL
A7: Nylas Cost / Site / Month | B7: 250350 | C7: IDR | D7: Hospitality integration API
A8: Junior Dev Salary / Month | B8: 3000000 | C8: IDR | D8: Ops + dev work
A9: Mid Dev Salary / Month | B9: 6000000 | C9: IDR | D9: Senior dev work
A10: Sites per Dev (ops) | B10: 10 | C10: sites | D10: Baseline ops capacity
A11: Custom Dev Buffer % | B11: 30 | C11: % | D11: Hospitality custom requests
A12: Domain Cost / Year (total) | B12: 800000 | C12: IDR | D12: Shared across 4 domains
A13: Domain Count | B13: 4 | C13: domains | D13: Existing domains

Sheet Infra_Labour_Logic
A1: Component | B1: Formula | C1: Result | D1: Notes
A2: Effective Sites / Dev | B2: Sites/dev × (1 - buffer) | C2: =Assumptions!B9*(1-Assumptions!B10/100) | D2: After custom buffer
A3: VPS Cost / Year (IDR) | B3: USD × FX × 12 | C3: =Assumptions!B2*Assumptions!B3*12 | D3: Yearly VPS cost
A4: VPS Cost / Site / Year | B4: VPS Year / Sites per VPS | C4: =C3/Assumptions!B4 | D4: Per site yearly
A5: VPS Cost / Site / Month | B5: VPS Year / Sites / 12 | C5: =C4/12 | D5: Per site monthly
A6: Labour Cost / Dev / Year | B6: Salary × 12 | C6: =Assumptions!B7*12 | D6: Per dev yearly
A7: Labour Cost / Site / Month | B7: Salary / Effective Sites | C7: =Assumptions!B7/C2 | D7: Per site monthly
A8: Labour Cost / Site / Year | B8: Monthly × 12 | C8: =C7*12 | D8: Per site yearly
A9: Domain Cost / Site / Year | B9: Total Domain / Sites | C9: =Assumptions!B11/Assumptions!B4 | D9: Per site yearly
A10: Domain Cost / Site / Month | B10: Yearly / 12 | C10: =C9/12 | D10: Per site monthly

Sheet Per_Site_Cost
A1: Component | B1: Per Month (IDR) | C1: Per Year (IDR) | D1: Notes
A2: VPS (shared) | B2: =Infra_Labour_Logic!C5 | C2: =Infra_Labour_Logic!C4 | D2: Shared VPS cost
A3: Nylas | B3: =Assumptions!B6 | C3: =Assumptions!B6*12 | D3: API service per site
A4: Labour (custom incl.) | B4: =Infra_Labour_Logic!C7 | C4: =Infra_Labour_Logic!C8 | D4: With 30% custom buffer
A5: Domain (shared) | B5: =Infra_Labour_Logic!C10 | C5: =Infra_Labour_Logic!C9 | D5: Shared domain cost
A6: TOTAL | B6: =SUM(B2:B5) | C6: =SUM(C2:C5) | D6: Total cost per site

Sheet Capacity_and_Hiring
A1: Total Sites | B1: Junior Dev | C1: Mid Dev | D1: VPS Required | E1: Notes
A2: 1 | B2: 1 | C2: 0 | D2: 1 | E2: Early stage
A3: 7 | B3: 1 | C3: 0 | D3: 1 | E3: Ops only
A4: 8 | B4: 2 | C4: 0 | D4: 1 | E4: Load increase
A5: 14 | B5: 2 | C5: 0 | D5: 2 | E5: Second VPS needed
A6: 15 | B6: 3 | C6: 1 | D6: 2 | E6: Custom requests heavy
A7: 25 | B7: 3 | C7: 1 | D7: 3 | E7: Scale up
A8: 30 | B8: 5 | C8: 2 | D8: 3 | E8: Team split
A9: 50 | B9: 5 | C9: 2 | D9: 5 | E9: Growth phase
A10: 60 | B10: 9 | C10: 2 | D10: 5 | E10: Mature stage

Sheet Budget_Summary
A1: Item | B1: Monthly (IDR) | C1: Yearly (IDR) | D1: Notes
A2: FIXED IT COST
A3: Junior Dev (1) | B3: =Assumptions!B7 | C3: =B3*12 | D3: Fixed manpower
A4: Mid Dev (0) | B4: 0 | C4: 0 | D4: Not yet needed
A5: VPS (amortized) | B5: =Infra_Labour_Logic!C3/12 | C5: =Infra_Labour_Logic!C3 | D5: Yearly VPS cost
A6: Subtotal Fixed | B6: =SUM(B3:B5) | C6: =SUM(C3:C5)
A8: VARIABLE COST
A9: Number of Sites | B9: 10
A10: Nylas | B10: =Per_Site_Cost!B3*B9 | C10: =Per_Site_Cost!C3*B9 | D10: Per site
A11: VPS share | B11: =Per_Site_Cost!B2*B9 | C11: =Per_Site_Cost!C2*B9 | D11: Per site
A12: Domain share | B12: =Per_Site_Cost!B5*B9 | C12: =Per_Site_Cost!C5*B9 | D12: Per site
A13: Subtotal Variable | B13: =SUM(B10:B12) | C13: =SUM(C10:C12)
A14: TOTAL IT BUDGET | B14: =B6+C13 | C14: =C6+C13

Sheet Budget_1_3_Years
A1: Year | B1: Sites | C1: VPS | D1: Junior Dev | E1: Mid Dev | F1: Infra / Year (IDR) | G1: Labour / Year (IDR) | H1: Total IT Cost / Year (IDR)
A2: 1 | B2: 12 | C2: =CEILING(B2/Assumptions!B4,1) | D2: =CEILING(B2/(Assumptions!B9*(1-Assumptions!B10/100)),1) | E2: 0 | F2: =C2*Infra_Labour_Logic!C3 | G2: =D2*Assumptions!B7*12 | H2: =F2+G2
A3: 2 | B3: 30 | C3: =CEILING(B3/Assumptions!B4,1) | D3: =CEILING(B3/(Assumptions!B9*(1-Assumptions!B10/100)),1) | E3: 1 | F3: =C3*Infra_Labour_Logic!C3 | G3: =D3*Assumptions!B7*12+E3*Assumptions!B8*12 | H3: =F3+G3
A4: 3 | B4: 60 | C4: =CEILING(B4/Assumptions!B4,1) | D4: =CEILING(B4/(Assumptions!B9*(1-Assumptions!B10/100)),1) | E4: 2 | F4: =C4*Infra_Labour_Logic!C3 | G4: =D4*Assumptions!B7*12+E4*Assumptions!B8*12 | H4: =F4+G4

Sheet Pricing_Tiers
A1: Tier | B1: Price / Month (IDR) | C1: Cost / Month (IDR) | D1: Margin / Month (IDR) | E1: Margin % | F1: Notes
A2: Basic | B2: 1200000 | C2: =Per_Site_Cost!B6 | D2: =B2-C2 | E2: =D2/B2*100 | F2: Entry level
A3: Pro | B3: 1800000 | C3: =Per_Site_Cost!B6 | D3: =B3-C3 | E3: =D3/B3*100 | F3: Sweet spot
A4: Enterprise | B4: 2500000 | C4: =Per_Site_Cost!B6 | D4: =B4-C4 | E4: =D4/B4*100 | F4: High margin

Sheet One_Time_Fees
A1: Item | B1: Fee (IDR) | C1: When Used | D1: Notes
A2: Initial Setup | B2: 3000000 | C2: Onboarding | D2: Domain, deploy, configuration
A3: Minor Custom Dev | B3: 5000000 | C3: Small requests | D3: Report, workflow kecil
A4: Major Custom Dev | B4: 15000000 | C4: Complex requests | D4: Logic booking, integration

Sheet Break_Even
A1: Item | B1: Value | C1: Unit | D1: Notes
A2: Avg Revenue / Site / Month | B2: =(Pricing_Tiers!B2+Pricing_Tiers!B3+Pricing_Tiers!B4)/3 | C2: IDR | D2: Average of 3 tiers
A3: Cost / Site / Month | B3: =Per_Site_Cost!B6 | C3: IDR | D3: Total cost per site
A4: Margin / Site / Month | B4: =B2-B3 | C4: IDR | D4: Profit per site
A5: Fixed Monthly Cost (min) | B5: =Budget_Summary!B6 | C5: IDR | D5: 1 VPS + 1 Dev minimum
A6: Break-even Customers | B6: =CEILING(B5/B4,1) | C6: customers | D6: Minimum customers needed

Sheet Hiring_Roadmap
A1: Stage | B1: Sites | C1: Junior | D1: Mid | E1: Focus | F1: Notes
A2: Early | B2: 1-15 | C2: 1 | D2: 0 | E2: Ops & bugfix | F2: Foundation
A3: Growth | B3: 16-40 | C3: 3 | D3: 1 | E3: Custom & refactor | F3: Scale up
A4: Scale | B4: 41-80 | C4: 5 | D4: 2 | E4: Split ops & dev | F4: Team structure
A5: Mature | B5: 80+ | C5: 8 | D5: 3 | E5: Team ownership | F5: Full team
